{
"type": "FeatureCollection",
"name": "well_points",
"crs": { "type": "name", "properties": { "name": "urn:ogc:def:crs:OGC:1.3:CRS84" } },
"features": [
{ "type": "Feature", "properties": { "id": 0 }, "geometry": { "type": "Point", "coordinates": [ 34.741789816773142, 3.761031691920525 ] } },
{ "type": "Feature", "properties": { "id": 1 }, "geometry": { "type": "Point", "coordinates": [ 34.741960074348874, 3.761324363577111 ] } },
{ "type": "Feature", "properties": { "id": 2 }, "geometry": { "type": "Point", "coordinates": [ 34.741199397166667, 3.761379139398412 ] } },
{ "type": "Feature", "properties": { "id": 3 }, "geometry": { "type": "Point", "coordinates": [ 34.741392730299253, 3.761709273057777 ] } },
{ "type": "Feature", "properties": { "id": 4 }, "geometry": { "type": "Point", "coordinates": [ 34.742953521672803, 3.761627362195103 ] } },
{ "type": "Feature", "properties": { "id": 5 }, "geometry": { "type": "Point", "coordinates": [ 34.742302348049819, 3.761926378175951 ] } },
{ "type": "Feature", "properties": { "id": 6 }, "geometry": { "type": "Point", "coordinates": [ 34.741820017955682, 3.762445501938607 ] } },
{ "type": "Feature", "properties": { "id": 7 }, "geometry": { "type": "Point", "coordinates": [ 34.742953693502969, 3.763047784929094 ] } },
{ "type": "Feature", "properties": { "id": 8 }, "geometry": { "type": "Point", "coordinates": [ 34.742831434726646, 3.764182790967194 ] } },
{ "type": "Feature", "properties": { "id": 9 }, "geometry": { "type": "Point", "coordinates": [ 34.744589398258029, 3.764472184537325 ] } },
{ "type": "Feature", "properties": { "id": 10 }, "geometry": { "type": "Point", "coordinates": [ 34.743370067911982, 3.765188040478534 ] } },
{ "type": "Feature", "properties": { "id": 11 }, "geometry": { "type": "Point", "coordinates": [ 34.743844118182516, 3.765979294904866 ] } },
{ "type": "Feature", "properties": { "id": 12 }, "geometry": { "type": "Point", "coordinates": [ 34.744339356145922, 3.766938423031704 ] } },
{ "type": "Feature", "properties": { "id": 13 }, "geometry": { "type": "Point", "coordinates": [ 34.74797375718655, 3.770504567001683 ] } },
{ "type": "Feature", "properties": { "id": 14 }, "geometry": { "type": "Point", "coordinates": [ 34.747085142683623, 3.770237520066415 ] } },
{ "type": "Feature", "properties": { "id": 15 }, "geometry": { "type": "Point", "coordinates": [ 34.747098561650652, 3.768964658764167 ] } },
{ "type": "Feature", "properties": { "id": 16 }, "geometry": { "type": "Point", "coordinates": [ 34.74672519990277, 3.768145421542031 ] } },
{ "type": "Feature", "properties": { "id": 17 }, "geometry": { "type": "Point", "coordinates": [ 34.746116922164141, 3.768533726756157 ] } },
{ "type": "Feature", "properties": { "id": 18 }, "geometry": { "type": "Point", "coordinates": [ 34.745801395150529, 3.768652124399794 ] } },
{ "type": "Feature", "properties": { "id": 19 }, "geometry": { "type": "Point", "coordinates": [ 34.746316501181049, 3.767710680529744 ] } },
{ "type": "Feature", "properties": { "id": 20 }, "geometry": { "type": "Point", "coordinates": [ 34.745029992073185, 3.765271374203802 ] } },
{ "type": "Feature", "properties": { "id": 21 }, "geometry": { "type": "Point", "coordinates": [ 34.742297000364395, 3.763227980101686 ] } },
{ "type": "Feature", "properties": { "id": 22 }, "geometry": { "type": "Point", "coordinates": [ 34.745089330271931, 3.766722126034599 ] } },
{ "type": "Feature", "properties": { "id": 23 }, "geometry": { "type": "Point", "coordinates": [ 34.744449597983696, 3.765651811032427 ] } },
{ "type": "Feature", "properties": { "id": 24 }, "geometry": { "type": "Point", "coordinates": [ 34.746759410414143, 3.769696536579709 ] } },
{ "type": "Feature", "properties": { "id": 25 }, "geometry": { "type": "Point", "coordinates": [ 34.746548866591837, 3.769313278453798 ] } },
{ "type": "Feature", "properties": { "id": 26 }, "geometry": { "type": "Point", "coordinates": [ 34.74737760321355, 3.769510004807735 ] } },
{ "type": "Feature", "properties": { "id": 27 }, "geometry": { "type": "Point", "coordinates": [ 34.741566900006696, 3.760483472343075 ] } },
{ "type": "Feature", "properties": { "id": 28 }, "geometry": { "type": "Point", "coordinates": [ 34.740586434431783, 3.760194462456501 ] } }
]
}
